nitricapi/__init__.py
nitricapi/nitric/__init__.py
nitricapi/nitric/document/__init__.py
nitricapi/nitric/document/v1/__init__.py
nitricapi/nitric/error/__init__.py
nitricapi/nitric/error/v1/__init__.py
nitricapi/nitric/event/__init__.py
nitricapi/nitric/event/v1/__init__.py
nitricapi/nitric/faas/__init__.py
nitricapi/nitric/faas/v1/__init__.py
nitricapi/nitric/queue/__init__.py
nitricapi/nitric/queue/v1/__init__.py
nitricapi/nitric/resource/__init__.py
nitricapi/nitric/resource/v1/__init__.py
nitricapi/nitric/secret/__init__.py
nitricapi/nitric/secret/v1/__init__.py
nitricapi/nitric/storage/__init__.py
nitricapi/nitric/storage/v1/__init__.py
nitricapi/validate/__init__.py
nitric_api-0.21.0.dist-info/LICENSE.txt
nitric_api-0.21.0.dist-info/METADATA
nitric_api-0.21.0.dist-info/WHEEL
nitric_api-0.21.0.dist-info/top_level.txt
nitric_api-0.21.0.dist-info/RECORD
