Metadata-Version: 2.1
Name: nitric-api
Version: 0.21.0
Summary: The Nitric base SDK for Python 3
Home-page: https://github.com/nitrictech/apis
Author: Nitric
Author-email: maintainers@nitric.io
License: UNKNOWN
Platform: UNKNOWN
Classifier: Programming Language :: Python :: 3
Classifier: Operating System :: OS Independent
Requires-Python: >=3.7
Requires-Dist: protobuf (==3.19.4)
Requires-Dist: betterproto (==2.0.0b5)
Requires-Dist: asyncio
Provides-Extra: dev
Requires-Dist: markupsafe (==2.0.1) ; extra == 'dev'
Requires-Dist: betterproto[compiler] (==2.0.0b5) ; extra == 'dev'
Requires-Dist: grpcio-tools (==1.44.0) ; extra == 'dev'
Requires-Dist: twine (==3.2.0) ; extra == 'dev'
